{
	"notice":
	[
        {"번호":21, "구분":"쇼핑",   "제목":"♣ 서비스 점검 안내",                                                           "날짜":"2020.08.08" },
        {"번호":20, "구분":"쇼핑",   "제목":"네이처컬렉션 쇼핑몰 배송비 정책변경 공지",                                       "날짜":"2020.08.04" },    
        {"번호":19, "구분":"브랜드", "제목":"[당첨자 발표] 7월 한달간 포토 리뷰 작성한 고객 중 우수 리뷰어 당첨자 발표",        "날짜":"2020.08.04" },    
        {"번호":18, "구분":"쇼핑",   "제목":"[당첨자 발표] fmgt 썸머 에디션 메이크업 박스 무료 증정 이벤트 당첨자 발표",        "날짜":"2020.07.23" },    
        {"번호":17, "구분":"쇼핑",   "제목":"[네이처컬렉션 서포터즈 5기 모집] 합격자 발표",        							  "날짜":"2020.07.22" },    
        {"번호":16, "구분":"브랜드", "제목":"네이처컬렉션 쇼핑몰 배송비 정책변경 공지",                                       "날짜":"2020.07.20" },    
		{"번호":15, "구분":"쇼핑",	 "제목":"♣ [네이처컬렉션 서포터즈 5기 모집] 합격자 발표", 							      "날짜":"2020.07.11" },
		{"번호":14, "구분":"쇼핑",	 "제목":"[매장수령안내] 딱6일간의 FREE GIFT 3 ~ 6일차 당첨고객 매장 수령 안내", 		   "날짜":"2020.07.10" },
		{"번호":13, "구분":"쇼핑",	 "제목":"♣ 서비스 점검 안내", 														    "날짜":"2020.07.07" },
		{"번호":12, "구분":"브랜드", "제목":"[매장수령안내] 딱6일간의 FREE GIFT 1,2일차 당첨고객 매장 수령 안내", 		       "날짜":"2020.07.07" },
		{"번호":11, "구분":"쇼핑",	 "제목":"[당첨자 발표] 네컬 웰컴 쿠폰북 증정 이벤트 6일차 당첨자 발표",  			        "날짜":"2020.07.06" },
		{"번호":10, "구분":"쇼핑",	 "제목":"[당첨자 발표] 딱6일간의 FREE GIFT 6일차 당첨자 발표👏🏻", 				            "날짜":"2020.07.06" },
		{"번호":9, "구분":"쇼핑",	 "제목":"[당첨자 발표] 네컬 웰컴 쿠폰북 증정 이벤트 5일차 당첨자 발표", 				    "날짜":"2020.07.05" },
		{"번호":8, "구분":"브랜드",	 "제목":"[당첨자 발표] 딱6일간의 FREE GIFT 5일차 당첨자 발표👏🏻", 				            "날짜":"2020.07.05" },
		{"번호":7, "구분":"쇼핑",	 "제목":"[당첨자 발표] 네컬 웰컴 쿠폰북 증정 이벤트 4일차 당첨자 발표", 				    "날짜":"2020.07.04" },
		{"번호":6, "구분":"브랜드",	 "제목":"[당첨자 발표] 네컬 웰컴 쿠폰북 증정 이벤트 3일차 당첨자 발표", 				    "날짜":"2020.07.04" },		
		{"번호":5, "구분":"쇼핑",	 "제목":"[당첨자 발표] 딱6일간의 FREE GIFT 3일차 당첨자 발표👏🏻", 				            "날짜":"2020.07.03" },		
		{"번호":4, "구분":"쇼핑",	 "제목":"[당첨자 발표] 딱6일간의 FREE GIFT 2일차 당첨자 발표👏🏻", 				            "날짜":"2020.07.03" },		
		{"번호":3, "구분":"브랜드",	 "제목":"[당첨자 발표] 네컬 웰컴 쿠폰북 증정 이벤트 1일차 당첨자 발표",				        "날짜":"2020.07.02" },
		{"번호":2, "구분":"쇼핑",	 "제목":"[당첨자 발표] 딱6일간의 FREE GIFT 1일차 당첨자 발표👏🏻", 				            "날짜":"2020.07.02" },
		{"번호":1, "구분":"쇼핑",	 "제목":"♣ 서비스 점검 안내", 											                 "날짜":"2020.06.24" }
	]
}